{"jobs" : [
    {
        "profile" : "Full Stack Developer",
         "salary" : "5lpa" , 
         "company" : "Deloitte",
         "location" : "Hyderabad"
         } ,
    {
        "profile" : "QA Engineer" , 
        "salary" :"4lpa" , 
        "company" : "TA Digital",
        "location" : "Gurgaon"
        } ,
    {
        "profile" : "HR Assistant", 
        "salary" : "3lpa" , 
        "company" : "Google",
        "location" : "Bangalore"
        } ,
    {
        "profile" : "Accounts Assistant", 
        "salary" : "6lpa" , 
        "company" : "Bank Of America",
        "location" : "Mumbai"
    } ,
    {
        "profile" : "Software Engineer", 
        "salary" : "12lpa" , 
        "company" : "Amazon",
        "location" : "Bangalore"
    }
] }